kaikki_json/__init__.py
kaikki_json/__main__.py
kaikki_json/_private/config.py
kaikki_json/_private/download.py
kaikki_json/_private/read.py
kaikki_json-0.1.1.dist-info/LICENSE
kaikki_json-0.1.1.dist-info/METADATA
kaikki_json-0.1.1.dist-info/WHEEL
kaikki_json-0.1.1.dist-info/top_level.txt
kaikki_json-0.1.1.dist-info/RECORD
