Metadata-Version: 2.1
Name: kaikki_json
Version: 0.1.1
Summary: Download and read Wiktionary data in JSON format, using Kaikki data dumps
Author-email: Michael Hoffman <mdhoffman271@gmail.com>
Project-URL: Homepage, https://github.com/mdhoffman271/KaikkiJson
Project-URL: Issues, https://github.com/mdhoffman271/KaikkiJson/issues
Classifier: Programming Language :: Python :: 3
Classifier: License :: OSI Approved :: MIT License
Classifier: Operating System :: OS Independent
Requires-Python: >=3.8
License-File: LICENSE
Requires-Dist: appdirs >=1.4.0
Requires-Dist: requests >=2.31.0
